[
  {
    "title": "في أي غار نزل الوحي لأول مرة على النبي ﷺ؟",
    "answer_1": "غار ثور",
    "answer_2": "غار حراء",
    "answer_3": "غار تبوك",
    "answer_4": "غار أحد",
    "right_answer": "غار حراء"
  },
  {
    "title": "كم كان عمر النبي ﷺ عندما نزل عليه الوحي؟",
    "answer_1": "25 سنة",
    "answer_2": "30 سنة",
    "answer_3": "40 سنة",
    "answer_4": "45 سنة",
    "right_answer": "40 سنة"
  },
  {
    "title": "من هي أول من أسلم من النساء؟",
    "answer_1": "عائشة بنت أبي بكر",
    "answer_2": "خديجة بنت خويلد",
    "answer_3": "فاطمة الزهراء",
    "answer_4": "أم سلمة",
    "right_answer": "خديجة بنت خويلد"
  },
  {
    "title": "إلى أين كانت الهجرة الأولى في الإسلام؟",
    "answer_1": "المدينة المنورة",
    "answer_2": "الحبشة",
    "answer_3": "الطائف",
    "answer_4": "اليمن",
    "right_answer": "الحبشة"
  },
  {
    "title": "ما هو الاسم القديم للمدينة المنورة قبل الهجرة؟",
    "answer_1": "مكة",
    "answer_2": "يثرب",
    "answer_3": "خيبر",
    "answer_4": "نجد",
    "right_answer": "يثرب"
  },
  {
    "title": "من هو رفيق النبي ﷺ في رحلة الهجرة إلى المدينة؟",
    "answer_1": "عمر بن الخطاب",
    "answer_2": "أبو بكر الصديق",
    "answer_3": "علي بن أبي طالب",
    "answer_4": "عثمان بن عفان",
    "right_answer": "أبو بكر الصديق"
  },
  {
    "title": "ما هي أول غزوة في الإسلام؟",
    "answer_1": "غزوة أحد",
    "answer_2": "غزوة بدر",
    "answer_3": "غزوة الخندق",
    "answer_4": "غزوة خيبر",
    "right_answer": "غزوة بدر"
  },
  {
    "title": "في أي سنة هجرية وقعت غزوة بدر الكبرى؟",
    "answer_1": "1 هـ",
    "answer_2": "2 هـ",
    "answer_3": "3 هـ",
    "answer_4": "4 هـ",
    "right_answer": "2 هـ"
  },
  {
    "title": "من الذي نام في فراش النبي ﷺ ليلة الهجرة؟",
    "answer_1": "علي بن أبي طالب",
    "answer_2": "زيد بن حارثة",
    "answer_3": "جعفر بن أبي طالب",
    "answer_4": "حمزة بن عبد المطلب",
    "right_answer": "علي بن أبي طالب"
  },
  {
    "title": "ما هي الغزوة التي هزم فيها المسلمون بسبب مخالفة الرماة لأمر النبي؟",
    "answer_1": "غزوة الخندق",
    "answer_2": "غزوة أحد",
    "answer_3": "غزوة حنين",
    "answer_4": "غزوة تبوك",
    "right_answer": "غزوة أحد"
  },
  {
    "title": "من هو الصحابي الذي أشار بحفر الخندق في غزوة الأحزاب؟",
    "answer_1": "خالد بن الوليد",
    "answer_2": "سلمان الفارسي",
    "answer_3": "بلال بن رباح",
    "answer_4": "عمار بن ياسر",
    "right_answer": "سلمان الفارسي"
  },
  {
    "title": "في أي سنة تم فتح مكة؟",
    "answer_1": "6 هـ",
    "answer_2": "7 هـ",
    "answer_3": "8 هـ",
    "answer_4": "10 هـ",
    "right_answer": "8 هـ"
  },
  {
    "title": "من هو الذي لُقب بـ 'سيف الله المسلول'؟",
    "answer_1": "حمزة بن عبد المطلب",
    "answer_2": "خالد بن الوليد",
    "answer_3": "علي بن أبي طالب",
    "answer_4": "سعد بن أبي وقاص",
    "right_answer": "خالد بن الوليد"
  },
  {
    "title": "من هو أول خليفة للمسلمين بعد وفاة النبي ﷺ؟",
    "answer_1": "عمر بن الخطاب",
    "answer_2": "أبو بكر الصديق",
    "answer_3": "عثمان بن عفان",
    "answer_4": "علي بن أبي طالب",
    "right_answer": "أبو بكر الصديق"
  },
  {
    "title": "ما هي المعركة التي انتهت بانتصار المسلمين على الفرس وسقوط دولتهم؟",
    "answer_1": "معركة اليرموك",
    "answer_2": "معركة القادسية",
    "answer_3": "معركة حطين",
    "answer_4": "معركة عين جالوت",
    "right_answer": "معركة القادسية"
  },
  {
    "title": "من هو الصحابي الذي لُقب بـ 'ذي النورين'؟",
    "answer_1": "عثمان بن عفان",
    "answer_2": "عمر بن الخطاب",
    "answer_3": "عبد الرحمن بن عوف",
    "answer_4": "طلحة بن عبيد الله",
    "right_answer": "عثمان بن عفان"
  },
  {
    "title": "في عهد أي خليفة تم جمع القرآن في مصحف واحد وتوزيعه على الأمصار؟",
    "answer_1": "أبو بكر الصديق",
    "answer_2": "عمر بن الخطاب",
    "answer_3": "عثمان بن عفان",
    "answer_4": "علي بن أبي طالب",
    "right_answer": "عثمان بن عفان"
  },
  {
    "title": "من هو القائد المسلم الذي فتح مصر؟",
    "answer_1": "عمر بن الخطاب",
    "answer_2": "عمرو بن العاص",
    "answer_3": "عقبة بن نافع",
    "answer_4": "طارق بن زياد",
    "right_answer": "عمرو بن العاص"
  },
  {
    "title": "ما هي المعركة التي وقعت بين المسلمين والروم في بلاد الشام؟",
    "answer_1": "معركة اليرموك",
    "answer_2": "معركة القادسية",
    "answer_3": "معركة نهوند",
    "answer_4": "معركة الجمل",
    "right_answer": "معركة اليرموك"
  },
  {
    "title": "من هو الخليفة الذي استشهد وهو يصلي الفجر في المسجد؟",
    "answer_1": "أبو بكر الصديق",
    "answer_2": "عمر بن الخطاب",
    "answer_3": "عثمان بن عفان",
    "answer_4": "علي بن أبي طالب",
    "right_answer": "عمر بن الخطاب"
  },
  {
    "title": "ما هو اسم الصلح الذي عقده النبي ﷺ مع قريش في السنة السادسة هجرية؟",
    "answer_1": "صلح المدينة",
    "answer_2": "صلح الحديبية",
    "answer_3": "صلح مكة",
    "answer_4": "صلح خيبر",
    "right_answer": "صلح الحديبية"
  },
  {
    "title": "من هو أول مؤذن في الإسلام؟",
    "answer_1": "أبو بكر الصديق",
    "answer_2": "بلال بن رباح",
    "answer_3": "سعد بن معاذ",
    "answer_4": "أسامة بن زيد",
    "right_answer": "بلال بن رباح"
  },
  {
    "title": "ما هي كنية النبي ﷺ؟",
    "answer_1": "أبو محمد",
    "answer_2": "أبو القاسم",
    "answer_3": "أبو إبراهيم",
    "answer_4": "أبو عبد الله",
    "right_answer": "أبو القاسم"
  },
  {
    "title": "من هو الصحابي الذي قتل جالوت في عهد طالوت؟",
    "answer_1": "النبي داود عليه السلام",
    "answer_2": "سليمان عليه السلام",
    "answer_3": "موسى عليه السلام",
    "answer_4": "يوشع بن نون",
    "right_answer": "النبي داود عليه السلام"
  },
  {
    "title": "ما هي الغزوة التي خرج فيها النبي ﷺ لمواجهة الروم ولم يحدث فيها قتال؟",
    "answer_1": "غزوة خيبر",
    "answer_2": "غزوة تبوك",
    "answer_3": "غزوة حنين",
    "answer_4": "غزوة الطائف",
    "right_answer": "غزوة تبوك"
  },
  {
    "title": "من هو الصحابي الذي لقب بـ 'أمين هذه الأمة'؟",
    "answer_1": "أبو عبيدة عامر بن الجراح",
    "answer_2": "سعد بن معاذ",
    "answer_3": "معاذ بن جبل",
    "answer_4": "أبو الدرداء",
    "right_answer": "أبو عبيدة عامر بن الجراح"
  },
  {
    "title": "كم استمرت الدعوة السرية في مكة؟",
    "answer_1": "سنة واحدة",
    "answer_2": "ثلاث سنوات",
    "answer_3": "خمس سنوات",
    "answer_4": "عشر سنوات",
    "right_answer": "ثلاث سنوات"
  },
  {
    "title": "من هي ابنة أبي بكر الصديق وزوجة النبي ﷺ؟",
    "answer_1": "حفصة",
    "answer_2": "عائشة",
    "answer_3": "زينب",
    "answer_4": "سودة",
    "right_answer": "عائشة"
  },
  {
    "title": "ما هي المعركة التي استشهد فيها حمزة بن عبد المطلب؟",
    "answer_1": "غزوة بدر",
    "answer_2": "غزوة أحد",
    "answer_3": "غزوة الخندق",
    "answer_4": "غزوة حنين",
    "right_answer": "غزوة أحد"
  },
  {
    "title": "من الذي قتل حمزة بن عبد المطلب ثم أسلم بعد ذلك؟",
    "answer_1": "أبو سفيان",
    "answer_2": "وحشي بن حرب",
    "answer_3": "خالد بن الوليد",
    "answer_4": "عكرمة بن أبي جهل",
    "right_answer": "وحشي بن حرب"
  },
  {
    "title": "ما هو الاسم الذي أطلقه النبي ﷺ على المدينة والأنصار تعبيراً عن المؤاخاة؟",
    "answer_1": "المهاجرون",
    "answer_2": "الأنصار",
    "answer_3": "الأصحاب",
    "answer_4": "التابعين",
    "right_answer": "الأنصار"
  },
  {
    "title": "من هو الملك الذي استقبل المهاجرين المسلمين في الحبشة؟",
    "answer_1": "هرقل",
    "answer_2": "النجاشي",
    "answer_3": "كسرى",
    "answer_4": "المقوقس",
    "right_answer": "النجاشي"
  },
  {
    "title": "في أي سنة توفي النبي ﷺ؟",
    "answer_1": "10 هـ",
    "answer_2": "11 هـ",
    "answer_3": "12 هـ",
    "answer_4": "13 هـ",
    "right_answer": "11 هـ"
  },
  {
    "title": "من هو الصحابي الذي كان يسمى بـ 'شاعر الرسول'؟",
    "answer_1": "حسان بن ثابت",
    "answer_2": "كعب بن مالك",
    "answer_3": "عبد الله بن رواحة",
    "answer_4": "الخنساء",
    "right_answer": "حسان بن ثابت"
  },
  {
    "title": "ما هي المعركة التي خاضها أبو بكر الصديق ضد المرتدين؟",
    "answer_1": "حروب الردة",
    "answer_2": "معركة الجمل",
    "answer_3": "معركة صفين",
    "answer_4": "معركة النهروان",
    "right_answer": "حروب الردة"
  },
  {
    "title": "من هو الصحابي الذي لُقب بـ 'الفاروق'؟",
    "answer_1": "أبو بكر الصديق",
    "answer_2": "عمر بن الخطاب",
    "answer_3": "علي بن أبي طالب",
    "answer_4": "عثمان بن عفان",
    "right_answer": "عمر بن الخطاب"
  },
  {
    "title": "ما هو أول مسجد بُني في الإسلام؟",
    "answer_1": "المسجد الحرام",
    "answer_2": "المسجد النبوي",
    "answer_3": "مسجد قباء",
    "answer_4": "المسجد الأقصى",
    "right_answer": "مسجد قباء"
  },
  {
    "title": "من هو قائد المسلمين في معركة القادسية؟",
    "answer_1": "سعد بن أبي وقاص",
    "answer_2": "خالد بن الوليد",
    "answer_3": "أبو عبيدة بن الجراح",
    "answer_4": "النعمان بن مقرن",
    "right_answer": "سعد بن أبي وقاص"
  },
  {
    "title": "من هو آخر الخلفاء الراشدين؟",
    "answer_1": "عثمان بن عفان",
    "answer_2": "علي بن أبي طالب",
    "answer_3": "الحسن بن علي",
    "answer_4": "عمر بن عبد العزيز",
    "right_answer": "علي بن أبي طالب"
  },
  {
    "title": "ما هي عاصمة الدولة الإسلامية في عهد علي بن أبي طالب؟",
    "answer_1": "المدينة المنورة",
    "answer_2": "الكوفة",
    "answer_3": "دمشق",
    "answer_4": "بغداد",
    "right_answer": "الكوفة"
  },
  {
    "title": "من هو الصحابي الذي لُقب بـ 'حبر الأمة'؟",
    "answer_1": "عبد الله بن مسعود",
    "answer_2": "عبد الله بن عباس",
    "answer_3": "عبد الله بن عمر",
    "answer_4": "زيد بن ثابت",
    "right_answer": "عبد الله بن عباس"
  },
  {
    "title": "ما هو الاسم الذي عُرف به عام وفاة خديجة بنت خويلد وأبو طالب؟",
    "answer_1": "عام الفيل",
    "answer_2": "عام الحزن",
    "answer_3": "عام الجماعة",
    "answer_4": "عام الرمادة",
    "right_answer": "عام الحزن"
  },
  {
    "title": "من هو الصحابي الذي أرسله النبي ﷺ مصعب بن عمير إلى المدينة لتعليم أهلها؟",
    "answer_1": "أول سفير في الإسلام",
    "answer_2": "داعية المدينة",
    "answer_3": "أمين السر",
    "answer_4": "خادم الرسول",
    "right_answer": "أول سفير في الإسلام"
  },
  {
    "title": "ما هي المعركة التي وقعت فيها حادثة 'التحكيم'؟",
    "answer_1": "معركة الجمل",
    "answer_2": "معركة صفين",
    "answer_3": "معركة النهروان",
    "answer_4": "معركة كربلاء",
    "right_answer": "معركة صفين"
  },
  {
    "title": "من هو الغلام الذي كان أول من أسلم من الصبيان؟",
    "answer_1": "علي بن أبي طالب",
    "answer_2": "زيد بن حارثة",
    "answer_3": "أسامة بن زيد",
    "answer_4": "عبد الله بن الزبير",
    "right_answer": "علي بن أبي طالب"
  },
  {
    "title": "من هو الصحابي الذي لُقب بـ 'أسد الله'؟",
    "answer_1": "حمزة بن عبد المطلب",
    "answer_2": "خالد بن الوليد",
    "answer_3": "علي بن أبي طالب",
    "answer_4": "عمر بن الخطاب",
    "right_answer": "حمزة بن عبد المطلب"
  },
  {
    "title": "ما هي المدينة التي حاصرها المسلمون في غزوة الأحزاب؟",
    "answer_1": "مكة",
    "answer_2": "المدينة المنورة",
    "answer_3": "الطائف",
    "answer_4": "خيبر",
    "right_answer": "المدينة المنورة"
  },
  {
    "title": "من هو الصحابي الذي كتب الوحي وكان من كبار جامعي القرآن؟",
    "answer_1": "زيد بن ثابت",
    "answer_2": "أبو هريرة",
    "answer_3": "أنس بن مالك",
    "answer_4": "معاوية بن أبي سفيان",
    "right_answer": "زيد بن ثابت"
  },
  {
    "title": "ما هي الغزوة التي انتهت بفتح حصون اليهود في شمال المدينة؟",
    "answer_1": "غزوة بني قريظة",
    "answer_2": "غزوة خيبر",
    "answer_3": "غزوة بني النضير",
    "answer_4": "غزوة تبوك",
    "right_answer": "غزوة خيبر"
  },
  {
    "title": "من هو الخليفة الذي أنشأ الدواوين ونظم التاريخ الهجري؟",
    "answer_1": "أبو بكر الصديق",
    "answer_2": "عمر بن الخطاب",
    "answer_3": "عثمان بن عفان",
    "answer_4": "علي بن أبي طالب",
    "right_answer": "عمر بن الخطاب"
  },
  {
    "title": "كم عدد آيات سورة الفاتحة؟",
    "answer_1": "5 آيات",
    "answer_2": "6 آيات",
    "answer_3": "7 آيات",
    "answer_4": "8 آيات",
    "right_answer": "7 آيات"
  },
  {
    "title": "كم عدد أرباع القرآن الكريم؟",
    "answer_1": "120 ربعاً",
    "answer_2": "240 ربعاً",
    "answer_3": "480 ربعاً",
    "answer_4": "60 ربعاً",
    "right_answer": "240 ربعاً"
  },
  {
    "title": "ما هي أطول كلمة في القرآن الكريم؟",
    "answer_1": "فأسقيناكموه",
    "answer_2": "أنلزمكموها",
    "answer_3": "فسيكفيكهم",
    "answer_4": "ليستخلفنهم",
    "right_answer": "فأسقيناكموه"
  },
  {
    "title": "ما هي السورة التي ذكرت فيها البسملة مرتين؟",
    "answer_1": "سورة النحل",
    "answer_2": "سورة النمل",
    "answer_3": "سورة يونس",
    "answer_4": "سورة الفاتحة",
    "right_answer": "سورة النمل"
  },
  {
    "title": "كم عدد السور التي بدأت بـ (الحروف المقطعة)؟",
    "answer_1": "25 سورة",
    "answer_2": "29 سورة",
    "answer_3": "30 سورة",
    "answer_4": "114 سورة",
    "right_answer": "29 سورة"
  },
  {
    "title": "كم عدد السور المدنية في القرآن الكريم؟",
    "answer_1": "28 سورة",
    "answer_2": "86 سورة",
    "answer_3": "20 سورة",
    "answer_4": "114 سورة",
    "right_answer": "28 سورة"
  },
  {
    "title": "ما هي السورة التي يبلغ عدد آياتها 30 آية وتُنجي من عذاب القبر؟",
    "answer_1": "سورة السجدة",
    "answer_2": "سورة الملك",
    "answer_3": "سورة الواقعة",
    "answer_4": "سورة يس",
    "right_answer": "سورة الملك"
  },
  {
    "title": "كم عدد سجدات التلاوة في القرآن الكريم؟",
    "answer_1": "10 سجدات",
    "answer_2": "12 سجدة",
    "answer_3": "15 سجدة",
    "answer_4": "14 سجدة",
    "right_answer": "15 سجدة"
  },
  {
    "title": "سورة بدأت وانتهت بالتسبيح، ما هي؟",
    "answer_1": "سورة الحشر",
    "answer_2": "سورة الأعلى",
    "answer_3": "سورة الحديد",
    "answer_4": "سورة الجمعة",
    "right_answer": "سورة الحشر"
  },
  {
    "title": "ما هي السورة التي بدأت باسم ثمرتين؟",
    "answer_1": "سورة النجم",
    "answer_2": "سورة التين",
    "answer_3": "سورة الرمان",
    "answer_4": "سورة الزيتون",
    "right_answer": "سورة التين"
  },
  {
    "title": "ما هي السورة التي تنتهي آياتها جميعاً بحرف السين؟",
    "answer_1": "سورة الإخلاص",
    "answer_2": "سورة الفلق",
    "answer_3": "سورة الناس",
    "answer_4": "سورة المسد",
    "right_answer": "سورة الناس"
  },
  {
    "title": "كم عدد المرات التي ذكر فيها اسم (عيسى) في القرآن؟",
    "answer_1": "10 مرات",
    "answer_2": "15 مرة",
    "answer_3": "25 مرة",
    "answer_4": "30 مرة",
    "right_answer": "25 مرة"
  },
  {
    "title": "ما هي السورة التي تسمى (عروس القرآن)؟",
    "answer_1": "سورة يس",
    "answer_2": "سورة الرحمن",
    "answer_3": "سورة الملك",
    "answer_4": "سورة الواقعة",
    "right_answer": "سورة الرحمن"
  },
  {
    "title": "كم عدد أجزاء القرآن الكريم؟",
    "answer_1": "20 جزءاً",
    "answer_2": "30 جزءاً",
    "answer_3": "60 جزءاً",
    "answer_4": "114 جزءاً",
    "right_answer": "30 جزءاً"
  },
  {
    "title": "ما هي أطول آية في القرآن الكريم؟",
    "answer_1": "آية الكرسي",
    "answer_2": "آية الدين",
    "answer_3": "آية المواريث",
    "answer_4": "آية المباهلة",
    "right_answer": "آية الدين"
  },
  {
    "title": "كم عدد سور القرآن الكريم؟",
    "answer_1": "110 سورة",
    "answer_2": "114 سورة",
    "answer_3": "120 سورة",
    "answer_4": "111 سورة",
    "right_answer": "114 سورة"
  },
  {
    "title": "ما هي السورة التي تخلو من حرف الراء؟",
    "answer_1": "سورة الإخلاص",
    "answer_2": "سورة الكوثر",
    "answer_3": "سورة الفلق",
    "answer_4": "سورة الفاتحة",
    "right_answer": "سورة الإخلاص"
  },
  {
    "title": "ما هي السورة التي لا تبدأ بالبسملة؟",
    "answer_1": "سورة التوبة",
    "answer_2": "سورة الأنفال",
    "answer_3": "سورة النمل",
    "answer_4": "سورة هود",
    "right_answer": "سورة التوبة"
  },
  {
    "title": "كم سورة في القرآن بدأت بـ (الحمد لله)؟",
    "answer_1": "3 سور",
    "answer_2": "4 سور",
    "answer_3": "5 سور",
    "answer_4": "6 سور",
    "right_answer": "5 سور"
  },
  {
    "title": "ما هو ترتيب سورة الناس في المصحف؟",
    "answer_1": "112",
    "answer_2": "113",
    "answer_3": "114",
    "answer_4": "111",
    "right_answer": "114"
  },
  {
    "title": "ما هي السورة التي تعدل ثلث القرآن؟",
    "answer_1": "سورة الإخلاص",
    "answer_2": "سورة الفاتحة",
    "answer_3": "سورة الكافرون",
    "answer_4": "سورة القدر",
    "right_answer": "سورة الإخلاص"
  },
  {
    "title": "في أي سورة وردت (آية الكرسي)؟",
    "answer_1": "سورة آل عمران",
    "answer_2": "سورة البقرة",
    "answer_3": "سورة النساء",
    "answer_4": "سورة المائدة",
    "right_answer": "سورة البقرة"
  },
  {
    "title": "ما هي السورة التي تسمى (سورة بني إسرائيل)؟",
    "answer_1": "سورة الإسراء",
    "answer_2": "سورة يوسف",
    "answer_3": "سورة القصص",
    "answer_4": "سورة مريم",
    "right_answer": "سورة الإسراء"
  },
  {
    "title": "كم عدد أحزاب القرآن الكريم؟",
    "answer_1": "30 حزباً",
    "answer_2": "60 حزباً",
    "answer_3": "120 حزباً",
    "answer_4": "40 حزباً",
    "right_answer": "60 حزباً"
  },
  {
    "title": "ما هي السورة التي حث الرسول النساء على تعلمها؟",
    "answer_1": "سورة النور",
    "answer_2": "سورة مريم",
    "answer_3": "سورة النساء",
    "answer_4": "سورة الأحزاب",
    "right_answer": "سورة النور"
  },
  {
    "title": "ما هي السورة التي تسمى (سورة التوديع)؟",
    "answer_1": "سورة الإخلاص",
    "answer_2": "سورة النصر",
    "answer_3": "سورة الكوثر",
    "answer_4": "سورة الفلق",
    "right_answer": "سورة النصر"
  },
  {
    "title": "من هو النبي الذي ذكر في القرآن أكثر من غيره؟",
    "answer_1": "النبي محمد ﷺ",
    "answer_2": "النبي عيسى عليه السلام",
    "answer_3": "النبي موسى عليه السلام",
    "answer_4": "النبي إبراهيم عليه السلام",
    "right_answer": "النبي موسى عليه السلام"
  },
  {
    "title": "ما هي السورة التي تسمى (سورة النعم)؟",
    "answer_1": "سورة النحل",
    "answer_2": "سورة الرحمن",
    "answer_3": "سورة الواقعة",
    "answer_4": "سورة الملك",
    "right_answer": "سورة النحل"
  },
  {
    "title": "ما هي السورة التي بدأت بكلمة (سورة)؟",
    "answer_1": "سورة البقرة",
    "answer_2": "سورة النور",
    "answer_3": "سورة الأحزاب",
    "answer_4": "سورة الإخلاص",
    "right_answer": "سورة النور"
  },
  {
    "title": "في أي سورة ورد ذكر قصة أصحاب الأخدود؟",
    "answer_1": "سورة البروج",
    "answer_2": "سورة الانشقاق",
    "answer_3": "سورة الطارق",
    "answer_4": "سورة الغاشية",
    "right_answer": "سورة البروج"
  },
  {
    "title": "ما هي السورة التي ختمت باسم وقت من أوقات الصلاة؟",
    "answer_1": "سورة الفجر",
    "answer_2": "سورة العصر",
    "answer_3": "سورة القدر",
    "answer_4": "سورة الضحى",
    "right_answer": "سورة القدر"
  },
  {
    "title": "في أي سورة ذكرت قصة ذي القرنين؟",
    "answer_1": "سورة الأنبياء",
    "answer_2": "سورة الكهف",
    "answer_3": "سورة ص",
    "answer_4": "سورة النمل",
    "right_answer": "سورة الكهف"
  },
  {
    "title": "ما هي السورة التي يطلق عليها (فسطاط القرآن)؟",
    "answer_1": "سورة البقرة",
    "answer_2": "سورة المائدة",
    "answer_3": "سورة الأعراف",
    "answer_4": "سورة الأنعام",
    "right_answer": "سورة البقرة"
  },
  {
    "title": "كم مرة ذكر لفظ (رمضان) في القرآن الكريم؟",
    "answer_1": "مرة واحدة",
    "answer_2": "مرتان",
    "answer_3": "ثلاث مرات",
    "answer_4": "أربع مرات",
    "right_answer": "مرة واحدة"
  },
  {
    "title": "ما هي السورة التي تسمى (قلب القرآن)؟",
    "answer_1": "سورة يس",
    "answer_2": "سورة البقرة",
    "answer_3": "سورة الكهف",
    "answer_4": "سورة طه",
    "right_answer": "سورة يس"
  },
  {
    "title": "كم سجدة تلاوة توجد في سورة الحج؟",
    "answer_1": "سجدة واحدة",
    "answer_2": "سجدتان",
    "answer_3": "ثلاث سجدات",
    "answer_4": "لا توجد سجدات",
    "right_answer": "سجدتان"
  },
  {
    "title": "ما هي السورة التي بدأت باسم ثمرتين؟",
    "answer_1": "سورة التين",
    "answer_2": "سورة النجم",
    "answer_3": "سورة الزيتون",
    "answer_4": "سورة العصر",
    "right_answer": "سورة التين"
  },
  {
    "title": "ما هي السورة التي تسمى (الفاضحة)؟",
    "answer_1": "سورة المنافقون",
    "answer_2": "سورة التوبة",
    "answer_3": "سورة الأحزاب",
    "answer_4": "سورة المجادلة",
    "right_answer": "سورة التوبة"
  },
  {
    "title": "ما هي السورة التي تسمى (أخت الطويلتين)؟",
    "answer_1": "سورة الأعراف",
    "answer_2": "سورة الأنعام",
    "answer_3": "سورة المائدة",
    "answer_4": "سورة النساء",
    "right_answer": "سورة الأعراف"
  },
  {
    "title": "ما هي السورة التي بدأت بكلمة (تَبَارَكَ) غير سورة الملك؟",
    "answer_1": "سورة الفرقان",
    "answer_2": "سورة المؤمنون",
    "answer_3": "سورة النور",
    "answer_4": "سورة الأحزاب",
    "right_answer": "سورة الفرقان"
  },
  {
    "title": "كم مرة وردت كلمة (يس) في القرآن الكريم؟",
    "answer_1": "مرة واحدة",
    "answer_2": "مرتان",
    "answer_3": "ثلاث مرات",
    "answer_4": "أربع مرات",
    "right_answer": "مرة واحدة"
  },
  {
    "title": "كم عدد السور التي سميت بأسماء الأنبياء؟",
    "answer_1": "4 سور",
    "answer_2": "5 سور",
    "answer_3": "6 سور",
    "answer_4": "7 سور",
    "right_answer": "6 سور"
  },
  {
    "title": "ما هي السورة التي بدأت بـ (يا أيها النبي)؟",
    "answer_1": "سورة التحريم",
    "answer_2": "سورة الأحزاب",
    "answer_3": "سورة الطلاق",
    "answer_4": "كل ما سبق صحيح",
    "right_answer": "كل ما سبق صحيح"
  },
  {
    "title": "كم مرة ذكر اسم (آدم) عليه السلام في القرآن؟",
    "answer_1": "10 مرات",
    "answer_2": "15 مرة",
    "answer_3": "25 مرة",
    "answer_4": "30 مرة",
    "right_answer": "25 مرة"
  },
  {
    "title": "ما هي السورة التي ذكرت فيها قصة قابيل وهابيل؟",
    "answer_1": "سورة البقرة",
    "answer_2": "سورة المائدة",
    "answer_3": "سورة الأعراف",
    "answer_4": "سورة يونس",
    "right_answer": "سورة المائدة"
  },
  {
    "title": "ما هي السورة التي تسمى (سنام القرآن)؟",
    "answer_1": "سورة آل عمران",
    "answer_2": "سورة البقرة",
    "answer_3": "سورة المائدة",
    "answer_4": "سورة النساء",
    "right_answer": "سورة البقرة"
  },
  {
    "title": "كم عدد أحرف كلمة (طه) في الرسم العثماني؟",
    "answer_1": "حرف واحد",
    "answer_2": "حرفان",
    "answer_3": "ثلاثة أحرف",
    "answer_4": "أربعة أحرف",
    "right_answer": "حرفان"
  },
  {
    "title": "ما هي السورة التي تسمى (سورة القتال)؟",
    "answer_1": "سورة الأنفال",
    "answer_2": "سورة التوبة",
    "answer_3": "سورة محمد",
    "answer_4": "سورة الفتح",
    "right_answer": "سورة محمد"
  },
  {
    "title": "في أي سنة هجرية فُرض الصيام على المسلمين؟",
    "answer_1": "السنة الأولى للهجرة",
    "answer_2": "السنة الثانية للهجرة",
    "answer_3": "السنة الثالثة للهجرة",
    "answer_4": "السنة الخامسة للهجرة",
    "right_answer": "السنة الثانية للهجرة"
  },
  {
    "title": "ما هو الركن الذي يمثله الصيام من أركان الإسلام؟",
    "answer_1": "الركن الثاني",
    "answer_2": "الركن الثالث",
    "answer_3": "الركن الرابع",
    "answer_4": "الركن الخامس",
    "right_answer": "الركن الرابع"
  },
  {
    "title": "ما هو اسم باب الجنة الذي لا يدخل منه إلا الصائمون؟",
    "answer_1": "باب الصلاة",
    "answer_2": "باب الجهاد",
    "answer_3": "باب الريان",
    "answer_4": "باب الصدقة",
    "right_answer": "باب الريان"
  },
  {
    "title": "ما حكم من أكل أو شرب في نهار رمضان ناسياً؟",
    "answer_1": "يبطل صيامه وعليه القضاء",
    "answer_2": "صيامه صحيح وليس عليه شيء",
    "answer_3": "عليه إطعام مسكين",
    "answer_4": "عليه القضاء والكفارة",
    "right_answer": "صيامه صحيح وليس عليه شيء"
  },
  {
    "title": "ما هي الليلة التي هي خير من ألف شهر؟",
    "answer_1": "ليلة الإسراء والمعراج",
    "answer_2": "ليلة القدر",
    "answer_3": "ليلة النصف من شعبان",
    "answer_4": "ليلة أول جمعة في رمضان",
    "right_answer": "ليلة القدر"
  },
  {
    "title": "متى يبدأ وقت الإمساك عن الطعام للصائم؟",
    "answer_1": "عند طلوع الفجر الصادق",
    "answer_2": "عند شروق الشمس",
    "answer_3": "قبل الفجر بساعة",
    "answer_4": "عند أذان الظهر",
    "right_answer": "عند طلوع الفجر الصادق"
  },
  {
    "title": "ما حكم صيام يوم الشك (يوم 30 شعبان)؟",
    "answer_1": "واجب",
    "answer_2": "مستحب",
    "answer_3": "منهي عنه",
    "answer_4": "مباح",
    "right_answer": "منهي عنه"
  },
  {
    "title": "كم عدد الأيام التي يجب صيامها في كفارة الظهار أو القتل الخطأ؟",
    "answer_1": "30 يوماً متتابعة",
    "answer_2": "60 يوماً متتابعة",
    "answer_3": "10 أيام",
    "answer_4": "40 يوماً متفرقة",
    "right_answer": "60 يوماً متتابعة"
  },
  {
    "title": "ما هي الغزوة التي وقعت في شهر رمضان المبارك؟",
    "answer_1": "غزوة أحد",
    "answer_2": "غزوة بدر الكبرى",
    "answer_3": "غزوة الخندق",
    "answer_4": "غزوة خيبر",
    "right_answer": "غزوة بدر الكبرى"
  },
  {
    "title": "صيام ستة أيام من شهر (...) يعدل صيام الدهر مع رمضان؟",
    "answer_1": "شعبان",
    "answer_2": "شوال",
    "answer_3": "ذو الحجة",
    "answer_4": "المحرم",
    "right_answer": "شوال"
  },
  {
    "title": "ما حكم القطرة في العين أو الأذن للصائم على الراجح؟",
    "answer_1": "تفطر مطلقاً",
    "answer_2": "لا تفطر",
    "answer_3": "تفطر إذا وصل طعمها للحلق",
    "answer_4": "مكروهة",
    "right_answer": "لا تفطر"
  },
  {
    "title": "أي من هؤلاء يباح له الفطر ويجب عليه القضاء فقط؟",
    "answer_1": "المريض مرضاً لا يرجى شفاؤه",
    "answer_2": "المسافر",
    "answer_3": "الكبير الطاعن في السن",
    "answer_4": "المجنون",
    "right_answer": "المسافر"
  },
  {
    "title": "ما هو فضل صيام يوم عرفة لغير الحاج؟",
    "answer_1": "يكفر سنة ماضية فقط",
    "answer_2": "يكفر سنة ماضية وسنة باقية",
    "answer_3": "يعدل صيام شهر",
    "answer_4": "ليس له فضل محدد",
    "right_answer": "يكفر سنة ماضية وسنة باقية"
  },
  {
    "title": "ماذا يسمى السحور في الأحاديث النبوية؟",
    "answer_1": "الغداء المبارك",
    "answer_2": "وجبة الصائم",
    "answer_3": "زاد المؤمن",
    "answer_4": "بركة النهار",
    "right_answer": "الغداء المبارك"
  },
  {
    "title": "متى ينتهي وقت صيام التطوع (مثل صيام الإثنين)؟",
    "answer_1": "عند العصر",
    "answer_2": "عند غروب الشمس",
    "answer_3": "قبل المغرب بساعة",
    "answer_4": "عند أذان العشاء",
    "right_answer": "عند غروب الشمس"
  },
  {
    "title": "ما هو الصيام المنهي عنه في الإسلام؟",
    "answer_1": "صيام يوم الجمعة منفرداً",
    "answer_2": "صيام يوم العيدين",
    "answer_3": "صيام أيام التشريق",
    "answer_4": "كل ما سبق",
    "right_answer": "كل ما سبق"
  },
  {
    "title": "ما حكم من جامع زوجته في نهار رمضان عمداً؟",
    "answer_1": "عليه القضاء فقط",
    "answer_2": "عليه الكفارة المغلظة والقضاء",
    "answer_3": "عليه إطعام مسكين",
    "answer_4": "ليس عليه شيء",
    "right_answer": "عليه الكفارة المغلظة والقضاء"
  },
  {
    "title": "ما هي الكفارة المغلظة لمن جامع في نهار رمضان؟",
    "answer_1": "صيام 3 أيام",
    "answer_2": "إطعام 10 مساكين",
    "answer_3": "عتق رقبة أو صيام شهرين متتابعين أو إطعام 60 مسكيناً",
    "answer_4": "صيام 10 أيام",
    "right_answer": "عتق رقبة أو صيام شهرين متتابعين أو إطعام 60 مسكيناً"
  },
  {
    "title": "ما حكم بخاخ الربو للصائم؟",
    "answer_1": "يفطر",
    "answer_2": "لا يفطر لأنه غاز مضغوط لا يصل للمعدة",
    "answer_3": "يفطر إذا استعمله مرتين",
    "answer_4": "مستحب",
    "right_answer": "لا يفطر لأنه غاز مضغوط لا يصل للمعدة"
  },
  {
    "title": "ما المقصود بـ 'الأيام البيض' التي يسن صيامها؟",
    "answer_1": "أول 3 أيام من الشهر",
    "answer_2": "أيام 13 و14 و15 من الشهر الهجري",
    "answer_3": "أيام الإثنين والخميس",
    "answer_4": "آخر 3 أيام من الشهر",
    "right_answer": "أيام 13 و14 و15 من الشهر الهجري"
  },
  {
    "title": "كم مرة ذكر الصيام في القرآن الكريم بمشتقاته؟",
    "answer_1": "5 مرات",
    "answer_2": "10 مرات",
    "answer_3": "14 مرة",
    "answer_4": "20 مرة",
    "right_answer": "14 مرة"
  },
  {
    "title": "ما هو 'صيام الوصال'؟",
    "answer_1": "وصل رمضان بشوال",
    "answer_2": "وصل صيام يومين أو أكثر دون فطر بينهما",
    "answer_3": "صيام يوم وإفطار يوم",
    "answer_4": "صيام الأيام البيض",
    "right_answer": "وصل صيام يومين أو أكثر دون فطر بينهما"
  },
  {
    "title": "ما هي السورة التي وردت فيها أحكام الصيام بالتفصيل؟",
    "answer_1": "سورة آل عمران",
    "answer_2": "سورة المائدة",
    "answer_3": "سورة البقرة",
    "answer_4": "سورة النساء",
    "right_answer": "سورة البقرة"
  },
  {
    "title": "ماذا يسن للصائم أن يفطر عليه؟",
    "answer_1": "الماء البارد",
    "answer_2": "التمر أو الرطب",
    "answer_3": "العصائر السكرية",
    "answer_4": "الخبز",
    "right_answer": "التمر أو الرطب"
  },
  {
    "title": "ما هو فضل صيام يوم عاشوراء؟",
    "answer_1": "يكفر السنة الماضية",
    "answer_2": "يكفر سنتين",
    "answer_3": "يعدل حجة",
    "answer_4": "يكفر الكبائر",
    "right_answer": "يكفر السنة الماضية"
  },
  {
    "title": "من هم الذين تجب عليهم الفدية (إطعام مسكين) دون القضاء؟",
    "answer_1": "المسافر",
    "answer_2": "المريض الذي لا يرجى برؤه والشيخ الفاني",
    "answer_3": "الحامل والمرضع",
    "answer_4": "الطالب في وقت الامتحانات",
    "right_answer": "المريض الذي لا يرجى برؤه والشيخ الفاني"
  },
  {
    "title": "متى تبدأ العشر الأواخر من رمضان؟",
    "answer_1": "ليلة 15",
    "answer_2": "ليلة 20",
    "answer_3": "ليلة 21",
    "answer_4": "ليلة 25",
    "right_answer": "ليلة 21"
  },
  {
    "title": "ما حكم نية الصيام في الفرض (رمضان)؟",
    "answer_1": "تجوز في نهار اليوم الأول",
    "answer_2": "يجب تبييتها من الليل قبل الفجر",
    "answer_3": "ليست واجبة",
    "answer_4": "تؤخذ بعد أذان الظهر",
    "right_answer": "يجب تبييتها من الليل قبل الفجر"
  },
  {
    "title": "ما هو 'الاعتكاف'؟",
    "answer_1": "الصلاة طوال الليل",
    "answer_2": "لزوم المسجد لطاعة الله وخاصة في رمضان",
    "answer_3": "توزيع الطعام على الفقراء",
    "answer_4": "قراءة القرآن في البيت",
    "right_answer": "لزوم المسجد لطاعة الله وخاصة في رمضان"
  },
  {
    "title": "ما حكم استخدام السواك للصائم؟",
    "answer_1": "محرم",
    "answer_2": "مكروه بعد الزوال",
    "answer_3": "سنة ومستحب في كل وقت",
    "answer_4": "يفطر الصائم",
    "right_answer": "سنة ومستحب في كل وقت"
  },
  {
    "title": "ما هو الدعاء المأثور عند الإفطار؟",
    "answer_1": "اللهم لك صمت وعلى رزقك أفطرت ذهب الظمأ وابتلت العروق",
    "answer_2": "الحمد لله الذي أطعمنا",
    "answer_3": "اللهم بارك لنا فيما رزقتنا",
    "answer_4": "يا حي يا قيوم",
    "right_answer": "اللهم لك صمت وعلى رزقك أفطرت ذهب الظمأ وابتلت العروق"
  },
  {
    "title": "ما معنى قوله صلى الله عليه وسلم 'خلوف فم الصائم'؟",
    "answer_1": "بقايا الطعام",
    "answer_2": "الرائحة المتغيرة من فمه لخلو معدته",
    "answer_3": "كلامه الطيب",
    "answer_4": "صمته عن اللغو",
    "right_answer": "الرائحة المتغيرة من فمه لخلو معدته"
  },
  {
    "title": "هل القيء غير العمد (ذرعه القيء) يبطل الصيام؟",
    "answer_1": "نعم يبطله",
    "answer_2": "لا يبطله",
    "answer_3": "يبطله ويوجب الكفارة",
    "answer_4": "مكروه",
    "right_answer": "لا يبطله"
  },
  {
    "title": "ما حكم شم البخور والعطور للصائم؟",
    "answer_1": "العطور لا تفطر، أما البخور فتكره استنشاقه بقوة لأنه له جرم يصل للمعدة",
    "answer_2": "يفطران مطلقاً",
    "answer_3": "مباحان تماماً",
    "answer_4": "محرمان",
    "right_answer": "العطور لا تفطر، أما البخور فتكره استنشاقه بقوة لأنه له جرم يصل للمعدة"
  },
  {
    "title": "ما هو أفضل الصيام بعد رمضان؟",
    "answer_1": "صيام شهر شوال",
    "answer_2": "صيام شهر الله المحرم",
    "answer_3": "صيام شهر شعبان",
    "answer_4": "صيام شهر ذو الحجة",
    "right_answer": "صيام شهر الله المحرم"
  },
  {
    "title": "أي من هذه الأيام يحرم صيامها؟",
    "answer_1": "يوم الجمعة",
    "answer_2": "يوم عرفة للحاج",
    "answer_3": "يوم النحر (أول أيام عيد الأضحى)",
    "answer_4": "يوم الإثنين",
    "right_answer": "يوم النحر (أول أيام عيد الأضحى)"
  },
  {
    "title": "من الذي قال عنه النبي صلى الله عليه وسلم: 'صام الدهر وفطر الدهر'؟",
    "answer_1": "من صام يوماً وأفطر يوماً",
    "answer_2": "من صام رمضان وأتبعه ستاً من شوال",
    "answer_3": "من صام الأيام البيض",
    "answer_4": "من صام شهر المحرم",
    "right_answer": "من صام رمضان وأتبعه ستاً من شوال"
  },
  {
    "title": "ما هو حكم صيام المسافر الذي يشق عليه الصيام شقة شديدة؟",
    "answer_1": "مستحب",
    "answer_2": "مباح",
    "answer_3": "مكروه أو منهي عنه",
    "answer_4": "واجب",
    "right_answer": "مكروه أو منهي عنه"
  },
  {
    "title": "ما هي الفدية الواجبة على من لا يستطيع الصيام أبداً؟",
    "answer_1": "إطعام مسكين عن كل يوم",
    "answer_2": "ذبح شاة",
    "answer_3": "صيام شهر آخر",
    "answer_4": "ليس عليه شيء",
    "right_answer": "إطعام مسكين عن كل يوم"
  },
  {
    "title": "بماذا يثبت دخول شهر رمضان؟",
    "answer_1": "برؤية الهلال أو إكمال شعبان 30 يوماً",
    "answer_2": "بالحساب الفلكي فقط",
    "answer_3": "بتوافق الناس",
    "answer_4": "عند رؤية النجوم",
    "right_answer": "برؤية الهلال أو إكمال شعبان 30 يوماً"
  },
  {
    "title": "ما حكم بلع الريق للصائم؟",
    "answer_1": "يفطر",
    "answer_2": "لا يفطر وهو معفو عنه للمشقة",
    "answer_3": "مكروه",
    "answer_4": "يفطر إذا كان كثيراً",
    "right_answer": "لا يفطر وهو معفو عنه للمشقة"
  },
  {
    "title": "ما هو السن الذي يؤمر فيه الصبي بالصيام للتعود؟",
    "answer_1": "سن 5 سنوات",
    "answer_2": "سن 7 أو 10 سنوات (إذا أطاق)",
    "answer_3": "سن 15 سنة",
    "answer_4": "عند دخول المدرسة",
    "right_answer": "سن 7 أو 10 سنوات (إذا أطاق)"
  },
  {
    "title": "ما حكم الحجامة للصائم على الراجح؟",
    "answer_1": "تفطر مطلقاً",
    "answer_2": "لا تفطر ولكن يكره فعلها إذا كانت تضعف الصائم",
    "answer_3": "واجبة",
    "answer_4": "تبطل الصلاة",
    "right_answer": "لا تفطر ولكن يكره فعلها إذا كانت تضعف الصائم"
  },
  {
    "title": "ما هي صلاة التراويح؟",
    "answer_1": "صلاة الفجر في رمضان",
    "answer_2": "صلاة القيام في جماعة في ليالي رمضان",
    "answer_3": "صلاة الضحى",
    "answer_4": "صلاة العيد",
    "right_answer": "صلاة القيام في جماعة في ليالي رمضان"
  },
  {
    "title": "كم عدد ركعات صلاة التراويح التي كان يصليها النبي غالباً؟",
    "answer_1": "20 ركعة",
    "answer_2": "11 ركعة أو 13 ركعة",
    "answer_3": "4 ركعات",
    "answer_4": "40 ركعة",
    "right_answer": "11 ركعة أو 13 ركعة"
  },
  {
    "title": "ما حكم تأخير السحور؟",
    "answer_1": "مكروه",
    "answer_2": "سنة مستحبة",
    "answer_3": "محرم",
    "answer_4": "لا فرق بين التعجيل والتأخير",
    "right_answer": "سنة مستحبة"
  },
  {
    "title": "ما حكم تعجيل الفطر؟",
    "answer_1": "سنة مستحبة فور التأكد من غروب الشمس",
    "answer_2": "مكروه",
    "answer_3": "واجب قبل الأذان",
    "answer_4": "بدعة",
    "right_answer": "سنة مستحبة فور التأكد من غروب الشمس"
  },
  {
    "title": "ما هي 'زكاة الفطر'؟",
    "answer_1": "صدقة تخرج في أول رمضان",
    "answer_2": "صدقة واجبة تخرج قبل صلاة عيد الفطر طهرة للصائم",
    "answer_3": "زكاة المال السنوية",
    "answer_4": "تبرع للمساجد",
    "right_answer": "صدقة واجبة تخرج قبل صلاة عيد الفطر طهرة للصائم"
  },
  {
    "title": "ما هو مقدار زكاة الفطر عن الفرد الواحد؟",
    "answer_1": "صاع من قوت البلد",
    "answer_2": "كيلو واحد فقط",
    "answer_3": "5 صاع",
    "answer_4": "نصف صاع",
    "right_answer": "صاع من قوت البلد"
  },
  {
    "title": "من هو 'الشيخ الفاني' في أحكام الصيام؟",
    "answer_1": "الرجل الصالح",
    "answer_2": "كبير السن الذي لا يقدر على الصيام",
    "answer_3": "إمام المسجد",
    "answer_4": "المسافر لمسافات طويلة",
    "right_answer": "كبير السن الذي لا يقدر على الصيام"
  },
  {
    "title": "من هو النبي الذي لُقب بـ 'ذو النون'؟",
    "answer_1": "يونس عليه السلام",
    "answer_2": "أيوب عليه السلام",
    "answer_3": "زكريا عليه السلام",
    "answer_4": "يحيى عليه السلام",
    "right_answer": "يونس عليه السلام"
  },
  {
    "title": "من هو النبي الذي صام عن الكلام لمدة ثلاثة أيام؟",
    "answer_1": "إبراهيم عليه السلام",
    "answer_2": "زكريا عليه السلام",
    "answer_3": "عيسى عليه السلام",
    "answer_4": "موسى عليه السلام",
    "right_answer": "زكريا عليه السلام"
  },
  {
    "title": "من هو النبي الذي آلان الله له الحديد؟",
    "answer_1": "سليمان عليه السلام",
    "answer_2": "داود عليه السلام",
    "answer_3": "يوسف عليه السلام",
    "answer_4": "صالح عليه السلام",
    "right_answer": "داود عليه السلام"
  },
  {
    "title": "من هو النبي الذي سخر الله له الريح والجن؟",
    "answer_1": "سليمان عليه السلام",
    "answer_2": "داود عليه السلام",
    "answer_3": "نوح عليه السلام",
    "answer_4": "هود عليه السلام",
    "right_answer": "سليمان عليه السلام"
  },
  {
    "title": "من هو النبي الذي صبر على المرض لسنوات طويلة؟",
    "answer_1": "يعقوب عليه السلام",
    "answer_2": "أيوب عليه السلام",
    "answer_3": "شعيب عليه السلام",
    "answer_4": "إدريس عليه السلام",
    "right_answer": "أيوب عليه السلام"
  },
  {
    "title": "من هو 'كليم الله' من الأنبياء؟",
    "answer_1": "محمد ﷺ",
    "answer_2": "موسى عليه السلام",
    "answer_3": "إبراهيم عليه السلام",
    "answer_4": "عيسى عليه السلام",
    "right_answer": "موسى عليه السلام"
  },
  {
    "title": "من هو النبي الذي بُعث إلى قوم ثمود؟",
    "answer_1": "هود عليه السلام",
    "answer_2": "صالح عليه السلام",
    "answer_3": "لوط عليه السلام",
    "answer_4": "شعيب عليه السلام",
    "right_answer": "صالح عليه السلام"
  },
  {
    "title": "من هو النبي الذي رفعه الله إلى السماء وهو حي؟",
    "answer_1": "عيسى عليه السلام",
    "answer_2": "إدريس عليه السلام",
    "answer_3": "كلاهما صحيح",
    "answer_4": "يحيى عليه السلام",
    "right_answer": "كلاهما صحيح"
  },
  {
    "title": "من هو النبي الذي كان يعمل خياطاً؟",
    "answer_1": "آدم عليه السلام",
    "answer_2": "إدريس عليه السلام",
    "answer_3": "نوح عليه السلام",
    "answer_4": "إبراهيم عليه السلام",
    "right_answer": "إدريس عليه السلام"
  },
  {
    "title": "من هو النبي الذي رأى 11 كوكباً والشمس والقمر يسجدون له؟",
    "answer_1": "يوسف عليه السلام",
    "answer_2": "يعقوب عليه السلام",
    "answer_3": "إسحاق عليه السلام",
    "answer_4": "إسماعيل عليه السلام",
    "right_answer": "يوسف عليه السلام"
  },
  {
    "title": "من هو النبي الذي بُعث إلى قوم مدين؟",
    "answer_1": "شعيب عليه السلام",
    "answer_2": "لوط عليه السلام",
    "answer_3": "هود عليه السلام",
    "answer_4": "صالح عليه السلام",
    "right_answer": "شعيب عليه السلام"
  },
  {
    "title": "من هو النبي الذي أُلقي في النار وخرج منها سالماً؟",
    "answer_1": "إبراهيم عليه السلام",
    "answer_2": "إسماعيل عليه السلام",
    "answer_3": "لوط عليه السلام",
    "answer_4": "هود عليه السلام",
    "right_answer": "إبراهيم عليه السلام"
  },
  {
    "title": "من هو النبي الذي بنى الكعبة مع ابنه إسماعيل؟",
    "answer_1": "آدم عليه السلام",
    "answer_2": "إبراهيم عليه السلام",
    "answer_3": "نوح عليه السلام",
    "answer_4": "شعيب عليه السلام",
    "right_answer": "إبراهيم عليه السلام"
  },
  {
    "title": "من هو النبي الذي كان يبرئ الأكمه والأبرص بإذن الله؟",
    "answer_1": "عيسى عليه السلام",
    "answer_2": "موسى عليه السلام",
    "answer_3": "يحيى عليه السلام",
    "answer_4": "أيوب عليه السلام",
    "right_answer": "عيسى عليه السلام"
  },
  {
    "title": "من هو النبي الذي لقب بـ 'خليل الله'؟",
    "answer_1": "محمد ﷺ",
    "answer_2": "إبراهيم عليه السلام",
    "answer_3": "إسماعيل عليه السلام",
    "answer_4": "إسحاق عليه السلام",
    "right_answer": "إبراهيم عليه السلام"
  },
  {
    "title": "من هو النبي الذي صارع ملك الموت؟",
    "answer_1": "موسى عليه السلام",
    "answer_2": "آدم عليه السلام",
    "answer_3": "إبراهيم عليه السلام",
    "answer_4": "نوح عليه السلام",
    "right_answer": "موسى عليه السلام"
  },
  {
    "title": "من هو النبي الذي كانت معجزته إحياء الموتى؟",
    "answer_1": "عيسى عليه السلام",
    "answer_2": "موسى عليه السلام",
    "answer_3": "صالح عليه السلام",
    "answer_4": "نوح عليه السلام",
    "right_answer": "عيسى عليه السلام"
  },
  {
    "title": "من هو النبي الذي عاش أكثر من 1000 عام؟",
    "answer_1": "آدم عليه السلام",
    "answer_2": "نوح عليه السلام",
    "answer_3": "إدريس عليه السلام",
    "answer_4": "شعيب عليه السلام",
    "right_answer": "نوح عليه السلام"
  },
  {
    "title": "من هو النبي الذي طلب منه قومه مائدة من السماء؟",
    "answer_1": "موسى عليه السلام",
    "answer_2": "عيسى عليه السلام",
    "answer_3": "إبراهيم عليه السلام",
    "answer_4": "محمد ﷺ",
    "right_answer": "عيسى عليه السلام"
  },
  {
    "title": "من هو النبي الذي كان والده كافراً؟",
    "answer_1": "إبراهيم عليه السلام",
    "answer_2": "نوح عليه السلام",
    "answer_3": "لوط عليه السلام",
    "answer_4": "يوسف عليه السلام",
    "right_answer": "إبراهيم عليه السلام"
  },
  {
    "title": "من هو النبي الذي سخر الله له الجبال تسبح معه؟",
    "answer_1": "سليمان عليه السلام",
    "answer_2": "داود عليه السلام",
    "answer_3": "موسى عليه السلام",
    "answer_4": "محمد ﷺ",
    "right_answer": "داود عليه السلام"
  },
  {
    "title": "من هو النبي الذي دعا ربه قائلًا: 'رَبِّ لَا تَذَرْنِي فَرْدًا'؟",
    "answer_1": "زكريا عليه السلام",
    "answer_2": "يحيى عليه السلام",
    "answer_3": "أيوب عليه السلام",
    "answer_4": "يونس عليه السلام",
    "right_answer": "زكريا عليه السلام"
  },
  {
    "title": "من هو النبي الذي اتخذه الله 'خليلاً'؟",
    "answer_1": "محمد ﷺ",
    "answer_2": "إبراهيم عليه السلام",
    "answer_3": "موسى عليه السلام",
    "answer_4": "عيسى عليه السلام",
    "right_answer": "إبراهيم عليه السلام"
  },
  {
    "title": "من هو النبي الذي سماه الله تعالى بنفسه قبل ولادته؟",
    "answer_1": "محمد ﷺ",
    "answer_2": "يحيى عليه السلام",
    "answer_3": "عيسى عليه السلام",
    "answer_4": "إسماعيل عليه السلام",
    "right_answer": "يحيى عليه السلام"
  },
  {
    "title": "من هو النبي الذي أُرسل إلى أهل أنطاكية؟",
    "answer_1": "حبيب النجار",
    "answer_2": "عيسى عليه السلام",
    "answer_3": "إلياس عليه السلام",
    "answer_4": "ثلاثة رسل",
    "right_answer": "ثلاثة رسل"
  },
  {
    "title": "من هو النبي الذي التهمه الحوت؟",
    "answer_1": "يونس عليه السلام",
    "answer_2": "أيوب عليه السلام",
    "answer_3": "نوح عليه السلام",
    "answer_4": "هود عليه السلام",
    "right_answer": "يونس عليه السلام"
  },
  {
    "title": "من هو النبي الذي نجا من الطوفان في السفينة؟",
    "answer_1": "نوح عليه السلام",
    "answer_2": "هود عليه السلام",
    "answer_3": "لوط عليه السلام",
    "answer_4": "إبراهيم عليه السلام",
    "right_answer": "نوح عليه السلام"
  },
  {
    "title": "من هو النبي الذي أرسل إلى قوم عاد؟",
    "answer_1": "هود عليه السلام",
    "answer_2": "صالح عليه السلام",
    "answer_3": "شعيب عليه السلام",
    "answer_4": "موسى عليه السلام",
    "right_answer": "هود عليه السلام"
  },
  {
    "title": "من هو النبي الذي كان له معجزة الناقة؟",
    "answer_1": "صالح عليه السلام",
    "answer_2": "هود عليه السلام",
    "answer_3": "يونس عليه السلام",
    "answer_4": "يوسف عليه السلام",
    "right_answer": "صالح عليه السلام"
  },
  {
    "title": "من هو النبي الذي بيع كعبد في مصر؟",
    "answer_1": "يوسف عليه السلام",
    "answer_2": "يعقوب عليه السلام",
    "answer_3": "موسى عليه السلام",
    "answer_4": "إسحاق عليه السلام",
    "right_answer": "يوسف عليه السلام"
  },
  {
    "title": "من هو النبي الذي تحولت عصاه إلى ثعبان؟",
    "answer_1": "موسى عليه السلام",
    "answer_2": "هارون عليه السلام",
    "answer_3": "عيسى عليه السلام",
    "answer_4": "داود عليه السلام",
    "right_answer": "موسى عليه السلام"
  },
  {
    "title": "من هو النبي الذي لقب بـ 'ذبيح الله'؟",
    "answer_1": "إسماعيل عليه السلام",
    "answer_2": "إسحاق عليه السلام",
    "answer_3": "يعقوب عليه السلام",
    "answer_4": "يوسف عليه السلام",
    "right_answer": "إسماعيل عليه السلام"
  },
  {
    "title": "من هو النبي الذي ولد من غير أب؟",
    "answer_1": "عيسى عليه السلام",
    "answer_2": "يحيى عليه السلام",
    "answer_3": "آدم عليه السلام",
    "answer_4": "إدريس عليه السلام",
    "right_answer": "عيسى عليه السلام"
  },
  {
    "title": "من هو النبي الذي رأى ربه في جبل الطور؟",
    "answer_1": "موسى عليه السلام",
    "answer_2": "إبراهيم عليه السلام",
    "answer_3": "داود عليه السلام",
    "answer_4": "سليمان عليه السلام",
    "right_answer": "موسى عليه السلام"
  },
  {
    "title": "من هو أول نبي من أولي العزم؟",
    "answer_1": "نوح عليه السلام",
    "answer_2": "إبراهيم عليه السلام",
    "answer_3": "آدم عليه السلام",
    "answer_4": "موسى عليه السلام",
    "right_answer": "نوح عليه السلام"
  },
  {
    "title": "من هو النبي الذي لقب بـ 'شيخ المرسلين'؟",
    "answer_1": "نوح عليه السلام",
    "answer_2": "إبراهيم عليه السلام",
    "answer_3": "آدم عليه السلام",
    "answer_4": "محمد ﷺ",
    "right_answer": "نوح عليه السلام"
  },
  {
    "title": "من هو النبي الذي كان ملكاً على الأرض كلها؟",
    "answer_1": "سليمان عليه السلام",
    "answer_2": "داود عليه السلام",
    "answer_3": "يوسف عليه السلام",
    "answer_4": "ذو القرنين",
    "right_answer": "سليمان عليه السلام"
  },
  {
    "title": "من هو النبي الذي كان يتحدث مع الهدهد؟",
    "answer_1": "سليمان عليه السلام",
    "answer_2": "نوح عليه السلام",
    "answer_3": "داود عليه السلام",
    "answer_4": "صالح عليه السلام",
    "right_answer": "سليمان عليه السلام"
  },
  {
    "title": "من هو النبي الذي فقد بصره حزناً على ابنه؟",
    "answer_1": "يعقوب عليه السلام",
    "answer_2": "إسحاق عليه السلام",
    "answer_3": "زكريا عليه السلام",
    "answer_4": "أيوب عليه السلام",
    "right_answer": "يعقوب عليه السلام"
  },
  {
    "title": "من هو النبي الذي قتله قومه بالمنشار؟",
    "answer_1": "زكريا عليه السلام",
    "answer_2": "يحيى عليه السلام",
    "answer_3": "شعيب عليه السلام",
    "answer_4": "حزقيل عليه السلام",
    "right_answer": "زكريا عليه السلام"
  },
  {
    "title": "من هو النبي الذي قطع رأسه وهو يصلي؟",
    "answer_1": "يحيى عليه السلام",
    "answer_2": "زكريا عليه السلام",
    "answer_3": "إسماعيل عليه السلام",
    "answer_4": "إلياس عليه السلام",
    "right_answer": "يحيى عليه السلام"
  },
  {
    "title": "من هو النبي الذي بشر بالسيد المسيح؟",
    "answer_1": "يحيى عليه السلام",
    "answer_2": "زكريا عليه السلام",
    "answer_3": "إشعياء عليه السلام",
    "answer_4": "داود عليه السلام",
    "right_answer": "يحيى عليه السلام"
  },
  {
    "title": "من هو النبي الذي أُرسل إلى قوم لوط؟",
    "answer_1": "لوط عليه السلام",
    "answer_2": "إبراهيم عليه السلام",
    "answer_3": "هود عليه السلام",
    "answer_4": "صالح عليه السلام",
    "right_answer": "لوط عليه السلام"
  },
  {
    "title": "من هو النبي الذي هاجر من العراق إلى فلسطين؟",
    "answer_1": "إبراهيم عليه السلام",
    "answer_2": "لوط عليه السلام",
    "answer_3": "موسى عليه السلام",
    "answer_4": "يونس عليه السلام",
    "right_answer": "إبراهيم عليه السلام"
  },
  {
    "title": "من هو النبي الذي كان له 12 ولداً؟",
    "answer_1": "يعقوب عليه السلام",
    "answer_2": "إسماعيل عليه السلام",
    "answer_3": "إسحاق عليه السلام",
    "answer_4": "يوسف عليه السلام",
    "right_answer": "يعقوب عليه السلام"
  },
  {
    "title": "من هو النبي الذي ضرب بعصاه البحر فانفلق؟",
    "answer_1": "موسى عليه السلام",
    "answer_2": "هارون عليه السلام",
    "answer_3": "يوشع بن نون",
    "answer_4": "إيليا عليه السلام",
    "right_answer": "موسى عليه السلام"
  },
  {
    "title": "من هو النبي الذي صعد إلى السماء في رحلة الإسراء؟",
    "answer_1": "محمد ﷺ",
    "answer_2": "عيسى عليه السلام",
    "answer_3": "إدريس عليه السلام",
    "answer_4": "إبراهيم عليه السلام",
    "right_answer": "محمد ﷺ"
  },
  {
    "title": "من هو النبي الذي كان صوته عذباً في التسبيح؟",
    "answer_1": "داود عليه السلام",
    "answer_2": "سليمان عليه السلام",
    "answer_3": "يحيى عليه السلام",
    "answer_4": "زكريا عليه السلام",
    "right_answer": "داود عليه السلام"
  },
  {
    "title": "من هو النبي الذي نطق في المهد صبياً؟",
    "answer_1": "عيسى عليه السلام",
    "answer_2": "يحيى عليه السلام",
    "answer_3": "محمد ﷺ",
    "answer_4": "إبراهيم عليه السلام",
    "right_answer": "عيسى عليه السلام"
  },
  {
    "title": "من هو النبي الذي بشر بقدوم النبي 'أحمد'؟",
    "answer_1": "عيسى عليه السلام",
    "answer_2": "موسى عليه السلام",
    "answer_3": "داود عليه السلام",
    "answer_4": "إبراهيم عليه السلام",
    "right_answer": "عيسى عليه السلام"
  },
  {
    "title": "ما هي أطول سورة في القرآن الكريم؟",
    "answer_1": "البقرة",
    "answer_2": "آل عمران",
    "answer_3": "النساء",
    "answer_4": "المائدة",
    "right_answer": "البقرة"
  },
  {
    "title": "ما هي أقصر سورة في القرآن الكريم؟",
    "answer_1": "الكوثر",
    "answer_2": "الإخلاص",
    "answer_3": "العصر",
    "answer_4": "النصر",
    "right_answer": "الكوثر"
  },
  {
    "title": "ما هي السورة التي تسمى 'عروس القرآن'؟",
    "answer_1": "الرحمن",
    "answer_2": "يس",
    "answer_3": "الواقعة",
    "answer_4": "الملك",
    "right_answer": "الرحمن"
  },
  {
    "title": "ما هي السورة التي تسمى 'قلب القرآن'؟",
    "answer_1": "يس",
    "answer_2": "الفاتحة",
    "answer_3": "الإخلاص",
    "answer_4": "البقرة",
    "right_answer": "يس"
  },
  {
    "title": "ما هي السورة التي تسمى 'أم الكتاب'؟",
    "answer_1": "الفاتحة",
    "answer_2": "البقرة",
    "answer_3": "يس",
    "answer_4": "الإخلاص",
    "right_answer": "الفاتحة"
  },
  {
    "title": "ما هي السورة التي تسمى 'المنجية'؟",
    "answer_1": "الملك",
    "answer_2": "السجدة",
    "answer_3": "يس",
    "answer_4": "الكهف",
    "right_answer": "الملك"
  },
  {
    "title": "كم عدد أجزاء القرآن الكريم؟",
    "answer_1": "30",
    "answer_2": "60",
    "answer_3": "114",
    "answer_4": "15",
    "right_answer": "30"
  },
  {
    "title": "كم عدد سور القرآن الكريم؟",
    "answer_1": "114",
    "answer_2": "110",
    "answer_3": "120",
    "answer_4": "100",
    "right_answer": "114"
  },
  {
    "title": "ما هي السورة التي لا تبدأ بالبسملة؟",
    "answer_1": "التوبة",
    "answer_2": "النمل",
    "answer_3": "العلق",
    "answer_4": "الفاتحة",
    "right_answer": "التوبة"
  },
  {
    "title": "ما هي السورة التي تحتوي على بسملتين؟",
    "answer_1": "النمل",
    "answer_2": "البقرة",
    "answer_3": "التوبة",
    "answer_4": "هود",
    "right_answer": "النمل"
  },
  {
    "title": "ما هي السورة التي تسمى 'سورة بني إسرائيل'؟",
    "answer_1": "الإسراء",
    "answer_2": "يونس",
    "answer_3": "القصص",
    "answer_4": "النمل",
    "right_answer": "الإسراء"
  },
  {
    "title": "ما هي السورة التي تسمى 'سورة القتال'؟",
    "answer_1": "محمد",
    "answer_2": "الأنفال",
    "answer_3": "التوبة",
    "answer_4": "الفتح",
    "right_answer": "محمد"
  },
  {
    "title": "ما هي السورة التي وردت فيها قصة أصحاب الكهف؟",
    "answer_1": "الكهف",
    "answer_2": "مريم",
    "answer_3": "طه",
    "answer_4": "الأنبياء",
    "right_answer": "الكهف"
  },
  {
    "title": "ما هي السورة التي وردت فيها قصة يوسف؟",
    "answer_1": "يوسف",
    "answer_2": "هود",
    "answer_3": "يونس",
    "answer_4": "الرعد",
    "right_answer": "يوسف"
  },
  {
    "title": "ما هي السورة التي تسمى 'سورة النعم'؟",
    "answer_1": "النحل",
    "answer_2": "النمل",
    "answer_3": "البقرة",
    "answer_4": "الرحمن",
    "right_answer": "النحل"
  },
  {
    "title": "ما هي السورة التي تسمى 'سورة النساء الصغرى'؟",
    "answer_1": "الطلاق",
    "answer_2": "التحريم",
    "answer_3": "الممتحنة",
    "answer_4": "المجادلة",
    "right_answer": "الطلاق"
  },
  {
    "title": "ما هي السورة التي تسمى 'المسبحات'؟",
    "answer_1": "التي تبدأ بسبح",
    "answer_2": "البقرة",
    "answer_3": "يس",
    "answer_4": "الفاتحة",
    "right_answer": "التي تبدأ بسبح"
  },
  {
    "title": "ما هي السورة التي تسمى 'الحواميم'؟",
    "answer_1": "التي تبدأ بحم",
    "answer_2": "التي تبدأ بسبح",
    "answer_3": "البقرة",
    "answer_4": "الكهف",
    "right_answer": "التي تبدأ بحم"
  },
  {
    "title": "ما هي السورة التي تسمى 'سورة التوديع'؟",
    "answer_1": "النصر",
    "answer_2": "الفتح",
    "answer_3": "المائدة",
    "answer_4": "البقرة",
    "right_answer": "النصر"
  },
  {
    "title": "ما هي السورة التي تسمى 'سورة الفاضحة'؟",
    "answer_1": "التوبة",
    "answer_2": "المنافقون",
    "answer_3": "الأحزاب",
    "answer_4": "النور",
    "right_answer": "التوبة"
  },
  {
    "title": "كم عدد السجدات في القرآن الكريم؟",
    "answer_1": "15",
    "answer_2": "10",
    "answer_3": "12",
    "answer_4": "14",
    "right_answer": "15"
  },
  {
    "title": "ما هو أول ما نزل من القرآن؟",
    "answer_1": "إقرأ باسم ربك",
    "answer_2": "الفاتحة",
    "answer_3": "المدثر",
    "answer_4": "المزمل",
    "right_answer": "إقرأ باسم ربك"
  },
  {
    "title": "ما هو آخر ما نزل من القرآن؟",
    "answer_1": "آية الربا",
    "answer_2": "واتقوا يوماً ترجعون",
    "answer_3": "اليوم أكملت لكم دينكم",
    "answer_4": "سورة النصر",
    "right_answer": "واتقوا يوماً ترجعون"
  },
  {
    "title": "من هو الصحابي الذي جمع القرآن في عهد أبي بكر؟",
    "answer_1": "زيد بن ثابت",
    "answer_2": "عثمان بن عفان",
    "answer_3": "علي بن أبي طالب",
    "answer_4": "أبي بن كعب",
    "right_answer": "زيد بن ثابت"
  },
  {
    "title": "من هو الخليفة الذي وحد المصاحف؟",
    "answer_1": "عثمان بن عفان",
    "answer_2": "عمر بن الخطاب",
    "answer_3": "علي بن أبي طالب",
    "answer_4": "أبو بكر الصديق",
    "right_answer": "عثمان بن عفان"
  },
  {
    "title": "ما هي أطول كلمة في القرآن الكريم؟",
    "answer_1": "فأسقيناكموه",
    "answer_2": "أنلزمكموها",
    "answer_3": "فسيكفيكهم",
    "answer_4": "المستضعفين",
    "right_answer": "فأسقيناكموه"
  },
  {
    "title": "كم عدد سور الجزء الثلاثين (جزء عم)؟",
    "answer_1": "37",
    "answer_2": "30",
    "answer_3": "40",
    "answer_4": "25",
    "right_answer": "37"
  },
  {
    "title": "ما هي السورة التي ذكرت فيها البسملة مرتين؟",
    "answer_1": "النمل",
    "answer_2": "هود",
    "answer_3": "النحل",
    "answer_4": "النمل",
    "right_answer": "النمل"
  },
  {
    "title": "ما هي السورة التي تنتهي آياتها بحرف السين؟",
    "answer_1": "الناس",
    "answer_2": "القدس",
    "answer_3": "الإخلاص",
    "answer_4": "الفلق",
    "right_answer": "الناس"
  },
  {
    "title": "ما هي السورة التي تسمى 'سورة الساهر'؟",
    "answer_1": "النازعات",
    "answer_2": "الواقعة",
    "answer_3": "المرسلات",
    "answer_4": "النبأ",
    "right_answer": "النازعات"
  },
  {
    "title": "ما هو الاسم الحقيقي لأبي بكر الصديق؟",
    "answer_1": "عبد الله بن أبي قحافة",
    "answer_2": "عثمان بن عفان",
    "answer_3": "عمر بن الخطاب",
    "answer_4": "علي بن أبي طالب",
    "right_answer": "عبد الله بن أبي قحافة"
  },
  {
    "title": "من هو الملقب بـ 'الفاروق'؟",
    "answer_1": "عمر بن الخطاب",
    "answer_2": "أبو بكر الصديق",
    "answer_3": "عثمان بن عفان",
    "answer_4": "علي بن أبي طالب",
    "right_answer": "عمر بن الخطاب"
  },
  {
    "title": "من هو الملقب بـ 'ذو النورين'؟",
    "answer_1": "عثمان بن عفان",
    "answer_2": "علي بن أبي طالب",
    "answer_3": "عمر بن الخطاب",
    "answer_4": "خالد بن الوليد",
    "right_answer": "عثمان بن عفان"
  },
  {
    "title": "من هو الملقب بـ 'أسد الله'؟",
    "answer_1": "حمزة بن عبد المطلب",
    "answer_2": "علي بن أبي طالب",
    "answer_3": "خالد بن الوليد",
    "answer_4": "عمر بن الخطاب",
    "right_answer": "حمزة بن عبد المطلب"
  },
  {
    "title": "من هو الملقب بـ 'سيف الله المسلول'؟",
    "answer_1": "خالد بن الوليد",
    "answer_2": "علي بن أبي طالب",
    "answer_3": "عمر بن الخطاب",
    "answer_4": "حمزة بن عبد المطلب",
    "right_answer": "خالد بن الوليد"
  },
  {
    "title": "من هو الملقب بـ 'أمين هذه الأمة'؟",
    "answer_1": "أبو عبيدة بن الجراح",
    "answer_2": "أبو بكر الصديق",
    "answer_3": "عمر بن الخطاب",
    "answer_4": "عثمان بن عفان",
    "right_answer": "أبو عبيدة بن الجراح"
  },
  {
    "title": "من هو الملقب بـ 'حبر الأمة'؟",
    "answer_1": "عبد الله بن عباس",
    "answer_2": "عبد الله بن مسعود",
    "answer_3": "عبد الله بن عمر",
    "answer_4": "زيد بن ثابت",
    "right_answer": "عبد الله بن عباس"
  },
  {
    "title": "من هو الملقب بـ 'صاحب سر رسول الله'؟",
    "answer_1": "حذيفة بن اليمان",
    "answer_2": "أبو بكر الصديق",
    "answer_3": "عمر بن الخطاب",
    "answer_4": "علي بن أبي طالب",
    "right_answer": "حذيفة بن اليمان"
  },
  {
    "title": "من هو أول مؤذن في الإسلام؟",
    "answer_1": "بلال بن رباح",
    "answer_2": "أبو بكر الصديق",
    "answer_3": "عمر بن الخطاب",
    "answer_4": "علي بن أبي طالب",
    "right_answer": "بلال بن رباح"
  },
  {
    "title": "من هو أول من جهر بالقرآن؟",
    "answer_1": "عبد الله بن مسعود",
    "answer_2": "أبو بكر الصديق",
    "answer_3": "عمر بن الخطاب",
    "answer_4": "علي بن أبي طالب",
    "right_answer": "عبد الله بن مسعود"
  },
  {
    "title": "من هو أول فدائي في الإسلام؟",
    "answer_1": "علي بن أبي طالب",
    "answer_2": "أبو بكر الصديق",
    "answer_3": "عمر بن الخطاب",
    "answer_4": "عثمان بن عفان",
    "right_answer": "علي بن أبي طالب"
  },
  {
    "title": "ما هي أول غزوة في الإسلام؟",
    "answer_1": "بدر الكبرى",
    "answer_2": "أحد",
    "answer_3": "الخندق",
    "answer_4": "خيبر",
    "right_answer": "بدر الكبرى"
  },
  {
    "title": "ما هي الغزوة التي جرح فيها النبي؟",
    "answer_1": "أحد",
    "answer_2": "بدر",
    "answer_3": "الخندق",
    "answer_4": "حنين",
    "right_answer": "أحد"
  },
  {
    "title": "ما هي الغزوة التي سميت بـ 'يوم الفرقان'؟",
    "answer_1": "بدر",
    "answer_2": "أحد",
    "answer_3": "الخندق",
    "answer_4": "خيبر",
    "right_answer": "بدر"
  },
  {
    "title": "ما هي الغزوة التي حفر فيها الخندق؟",
    "answer_1": "الأحزاب",
    "answer_2": "بدر",
    "answer_3": "أحد",
    "answer_4": "تبوك",
    "right_answer": "الأحزاب"
  },
  {
    "title": "ما هي آخر غزوة قادها النبي؟",
    "answer_1": "تبوك",
    "answer_2": "خيبر",
    "answer_3": "حنين",
    "answer_4": "مكة",
    "right_answer": "تبوك"
  },
  {
    "title": "كم عدد زوجات النبي محمد ﷺ؟",
    "answer_1": "11",
    "answer_2": "10",
    "answer_3": "12",
    "answer_4": "9",
    "right_answer": "11"
  },
  {
    "title": "من هي أول زوجة للنبي محمد ﷺ؟",
    "answer_1": "خديجة بنت خويلد",
    "answer_2": "عائشة بنت أبي بكر",
    "answer_3": "سودة بنت زمعة",
    "answer_4": "حفصة بنت عمر",
    "right_answer": "خديجة بنت خويلد"
  },
  {
    "title": "من هي الزوجة الوحيدة البكر للنبي؟",
    "answer_1": "عائشة بنت أبي بكر",
    "answer_2": "خديجة بنت خويلد",
    "answer_3": "حفصة بنت عمر",
    "answer_4": "زينب بنت جحش",
    "right_answer": "عائشة بنت أبي بكر"
  },
  {
    "title": "من هي الملقبة بـ 'أم المساكين'؟",
    "answer_1": "زينب بنت خزيمة",
    "answer_2": "خديجة بنت خويلد",
    "answer_3": "عائشة بنت أبي بكر",
    "answer_4": "حفصة بنت عمر",
    "right_answer": "زينب بنت خزيمة"
  },
  {
    "title": "ما هو اسم والدة النبي محمد ﷺ؟",
    "answer_1": "آمنة بنت وهب",
    "answer_2": "حليمة السعدية",
    "answer_3": "فاطمة بنت أسد",
    "answer_4": "خديجة بنت خويلد",
    "right_answer": "آمنة بنت وهب"
  },
  {
    "title": "ما هو اسم مرضعة النبي محمد ﷺ؟",
    "answer_1": "حليمة السعدية",
    "answer_2": "آمنة بنت وهب",
    "answer_3": "ثويبة الأسلمية",
    "answer_4": "كلاهما (حليمة وثويبة)",
    "right_answer": "كلاهما (حليمة وثويبة)"
  },
  {
    "title": "كم عدد أبناء النبي محمد ﷺ من الذكور؟",
    "answer_1": "3",
    "answer_2": "2",
    "answer_3": "4",
    "answer_4": "1",
    "right_answer": "3"
  },
  {
    "title": "كم عدد بنات النبي محمد ﷺ؟",
    "answer_1": "4",
    "answer_2": "3",
    "answer_3": "2",
    "answer_4": "5",
    "right_answer": "4"
  },
  {
    "title": "ما هو اسم أكبر بنات النبي محمد ﷺ؟",
    "answer_1": "زينب",
    "answer_2": "رقية",
    "answer_3": "أم كلثوم",
    "answer_4": "فاطمة",
    "right_answer": "زينب"
  },
  {
    "title": "من هو زوج فاطمة الزهراء؟",
    "answer_1": "علي بن أبي طالب",
    "answer_2": "عثمان بن عفان",
    "answer_3": "أبو بكر الصديق",
    "answer_4": "عمر بن الخطاب",
    "right_answer": "علي بن أبي طالب"
  },
  {
    "title": "من هما 'سيدا شباب أهل الجنة'؟",
    "answer_1": "الحسن والحسين",
    "answer_2": "علي وحمزة",
    "answer_3": "أبو بكر وعمر",
    "answer_4": "زيد وأسامة",
    "right_answer": "الحسن والحسين"
  },
  {
    "title": "كم ركعة في صلاة الفجر؟",
    "answer_1": "2",
    "answer_2": "3",
    "answer_3": "4",
    "answer_4": "1",
    "right_answer": "2"
  },
  {
    "title": "كم ركعة في صلاة المغرب؟",
    "answer_1": "3",
    "answer_2": "2",
    "answer_3": "4",
    "answer_4": "1",
    "right_answer": "3"
  },
  {
    "title": "ما هي الصلاة التي ليس لها ركوع ولا سجود؟",
    "answer_1": "صلاة الجنازة",
    "answer_2": "صلاة العيد",
    "answer_3": "صلاة الكسوف",
    "answer_4": "صلاة الخوف",
    "right_answer": "صلاة الجنازة"
  },
  {
    "title": "ما هي أول صلاة صلاها النبي بعد فرض الصلوات؟",
    "answer_1": "الظهر",
    "answer_2": "الفجر",
    "answer_3": "المغرب",
    "answer_4": "العصر",
    "right_answer": "الظهر"
  },
  {
    "title": "ما هو الركن الثالث من أركان الإسلام؟",
    "answer_1": "الزكاة",
    "answer_2": "الصلاة",
    "answer_3": "الصيام",
    "answer_4": "الحج",
    "right_answer": "الزكاة"
  },
  {
    "title": "ما هو الركن الرابع من أركان الإسلام؟",
    "answer_1": "الصيام",
    "answer_2": "الزكاة",
    "answer_3": "الحج",
    "answer_4": "الصلاة",
    "right_answer": "الصيام"
  },
  {
    "title": "كم عدد أركان الإيمان؟",
    "answer_1": "6",
    "answer_2": "5",
    "answer_3": "7",
    "answer_4": "4",
    "right_answer": "6"
  },
  {
    "title": "ما هو الركن الأول من أركان الإيمان؟",
    "answer_1": "الإيمان بالله",
    "answer_2": "الإيمان بالملائكة",
    "answer_3": "الإيمان بالكتب",
    "answer_4": "الإيمان بالرسل",
    "right_answer": "الإيمان بالله"
  },
  {
    "title": "ما هي القبلة الأولى للمسلمين؟",
    "answer_1": "المسجد الأقصى",
    "answer_2": "المسجد الحرام",
    "answer_3": "مسجد قباء",
    "answer_4": "المسجد النبوي",
    "right_answer": "المسجد الأقصى"
  },
  {
    "title": "ما هو المسجد الذي تشد إليه الرحال؟",
    "answer_1": "المسجد الحرام",
    "answer_2": "المسجد النبوي",
    "answer_3": "المسجد الأقصى",
    "answer_4": "جميع ما سبق",
    "right_answer": "جميع ما سبق"
  },
  {
    "title": "ما هو أعظم آية في القرآن الكريم؟",
    "answer_1": "آية الكرسي",
    "answer_2": "آية الدين",
    "answer_3": "سورة الإخلاص",
    "answer_4": "آية الملك",
    "right_answer": "آية الكرسي"
  },
  {
    "title": "ما هي 'باقيات الصالحات'؟",
    "answer_1": "سبحان الله والحمد لله ولا إله إلا الله والله أكبر",
    "answer_2": "الصلاة والصوم",
    "answer_3": "الزكاة والحج",
    "answer_4": "بر الوالدين",
    "right_answer": "سبحان الله والحمد لله ولا إله إلا الله والله أكبر"
  },
  {
    "title": "من هو النبي الذي بنى السفينة؟",
    "answer_1": "نوح عليه السلام",
    "answer_2": "إبراهيم عليه السلام",
    "answer_3": "آدم عليه السلام",
    "answer_4": "موسى عليه السلام",
    "right_answer": "نوح عليه السلام"
  },
  {
    "title": "من هو النبي الذي نجا من النار؟",
    "answer_1": "إبراهيم عليه السلام",
    "answer_2": "موسى عليه السلام",
    "answer_3": "عيسى عليه السلام",
    "answer_4": "يونس عليه السلام",
    "right_answer": "إبراهيم عليه السلام"
  },
  {
    "title": "من هو النبي الذي انفلق له البحر؟",
    "answer_1": "موسى عليه السلام",
    "answer_2": "نوح عليه السلام",
    "answer_3": "إبراهيم عليه السلام",
    "answer_4": "داود عليه السلام",
    "right_answer": "موسى عليه السلام"
  },
  {
    "title": "من هو النبي الذي كلم ربه في الوادي المقدس؟",
    "answer_1": "موسى عليه السلام",
    "answer_2": "محمد ﷺ",
    "answer_3": "عيسى عليه السلام",
    "answer_4": "يحيى عليه السلام",
    "right_answer": "موسى عليه السلام"
  },
  {
    "title": "من هو النبي الذي ألقي في الجب؟",
    "answer_1": "يوسف عليه السلام",
    "answer_2": "يعقوب عليه السلام",
    "answer_3": "إسحاق عليه السلام",
    "answer_4": "إسماعيل عليه السلام",
    "right_answer": "يوسف عليه السلام"
  },
  {
    "title": "من هو النبي الذي نجا من بطن الحوت؟",
    "answer_1": "يونس عليه السلام",
    "answer_2": "أيوب عليه السلام",
    "answer_3": "نوح عليه السلام",
    "answer_4": "زكريا عليه السلام",
    "right_answer": "يونس عليه السلام"
  },
  {
    "title": "من هو النبي الذي كان يصنع من الطين طيراً؟",
    "answer_1": "عيسى عليه السلام",
    "answer_2": "موسى عليه السلام",
    "answer_3": "سليمان عليه السلام",
    "answer_4": "إبراهيم عليه السلام",
    "right_answer": "عيسى عليه السلام"
  },
  {
    "title": "من هو النبي الذي كان ملكاً وابن ملك؟",
    "answer_1": "سليمان بن داود",
    "answer_2": "يوسف بن يعقوب",
    "answer_3": "يحيى بن زكريا",
    "answer_4": "عيسى بن مريم",
    "right_answer": "سليمان بن داود"
  },
  {
    "title": "من هو النبي الذي كان يفهم لغة الحيوانات؟",
    "answer_1": "سليمان عليه السلام",
    "answer_2": "داود عليه السلام",
    "answer_3": "نوح عليه السلام",
    "answer_4": "صالح عليه السلام",
    "right_answer": "سليمان عليه السلام"
  },
  {
    "title": "من هو النبي الذي اشتهر بصبره الشديد؟",
    "answer_1": "أيوب عليه السلام",
    "answer_2": "يعقوب عليه السلام",
    "answer_3": "يوسف عليه السلام",
    "answer_4": "موسى عليه السلام",
    "right_answer": "أيوب عليه السلام"
  },
  {
    "title": "من هو النبي الذي لقب بـ 'صفي الله'؟",
    "answer_1": "آدم عليه السلام",
    "answer_2": "شيث عليه السلام",
    "answer_3": "إدريس عليه السلام",
    "answer_4": "نوح عليه السلام",
    "right_answer": "آدم عليه السلام"
  },
  {
    "title": "ما هو اسم ناقة النبي ﷺ التي هاجر بها؟",
    "answer_1": "القصواء",
    "answer_2": "العضباء",
    "answer_3": "الصهباء",
    "answer_4": "الجدعاء",
    "right_answer": "القصواء"
  },
  {
    "title": "ما هو اسم سيف النبي ﷺ المشهور؟",
    "answer_1": "ذو الفقار",
    "answer_2": "البتار",
    "answer_3": "العضب",
    "answer_4": "الصمصام",
    "right_answer": "ذو الفقار"
  },
  {
    "title": "كم عدد السنوات التي نزل فيها القرآن؟",
    "answer_1": "23",
    "answer_2": "20",
    "answer_3": "25",
    "answer_4": "13",
    "right_answer": "23"
  },
  {
    "title": "ما هي السورة التي تسمى 'سورة الأنبياء'؟",
    "answer_1": "الأنبياء",
    "answer_2": "يس",
    "answer_3": "الكهف",
    "answer_4": "الشعراء",
    "right_answer": "الأنبياء"
  },
  {
    "title": "ما هي السورة التي ذكر فيها النحل؟",
    "answer_1": "النحل",
    "answer_2": "النمل",
    "answer_3": "البقرة",
    "answer_4": "العنكبوت",
    "right_answer": "النحل"
  },
  {
    "title": "ما هي السورة التي ذكر فيها النمل؟",
    "answer_1": "النمل",
    "answer_2": "النحل",
    "answer_3": "العلق",
    "answer_4": "الفيل",
    "right_answer": "النمل"
  },
  {
    "title": "ما هي السورة التي تسمى 'سورة الفيل'؟",
    "answer_1": "الفيل",
    "answer_2": "الهمزة",
    "answer_3": "القارعة",
    "answer_4": "العاديات",
    "right_answer": "الفيل"
  },
  {
    "title": "كم عدد سجدات القرآن المتفق عليها؟",
    "answer_1": "15",
    "answer_2": "14",
    "answer_3": "12",
    "answer_4": "10",
    "right_answer": "15"
  },
  {
    "title": "ما هو اسم الملك الموكل بالمطر؟",
    "answer_1": "ميكائيل",
    "answer_2": "جبريل",
    "answer_3": "إسرافيل",
    "answer_4": "رضوان",
    "right_answer": "ميكائيل"
  },
  {
    "title": "ما هو اسم الملك خازن الجنة؟",
    "answer_1": "رضوان",
    "answer_2": "مالك",
    "answer_3": "منكر",
    "answer_4": "نكير",
    "right_answer": "رضوان"
  },
  {
    "title": "ما هو اسم الملك خازن النار؟",
    "answer_1": "مالك",
    "answer_2": "رضوان",
    "answer_3": "عزرائيل",
    "answer_4": "إسرافيل",
    "right_answer": "مالك"
  },
  {
    "title": "كم عدد أبواب النار؟",
    "answer_1": "7",
    "answer_2": "8",
    "answer_3": "6",
    "answer_4": "5",
    "right_answer": "7"
  },
  {
    "title": "كم عدد أبواب الجنة؟",
    "answer_1": "8",
    "answer_2": "7",
    "answer_3": "10",
    "answer_4": "12",
    "right_answer": "8"
  },
  {
    "title": "ما هو اسم الباب المخصص للصائمين؟",
    "answer_1": "الريان",
    "answer_2": "الصلوات",
    "answer_3": "الجهاد",
    "answer_4": "الصدقة",
    "right_answer": "الريان"
  },
  {
    "title": "ما هي الشجرة الملعونة في القرآن؟",
    "answer_1": "الزقوم",
    "answer_2": "السدر",
    "answer_3": "الزيتون",
    "answer_4": "النخيل",
    "right_answer": "الزقوم"
  },
  {
    "title": "ما هو الشراب المذكور فيه شفاء للناس؟",
    "answer_1": "العسل",
    "answer_2": "الماء",
    "answer_3": "اللبن",
    "answer_4": "الخمر",
    "right_answer": "العسل"
  },
  {
    "title": "ما هي السورة التي تسمى 'سورة الحديد'؟",
    "answer_1": "الحديد",
    "answer_2": "النحاس",
    "answer_3": "الذهب",
    "answer_4": "الفضة",
    "right_answer": "الحديد"
  },
  {
    "title": "ما هو أول جبل وضع في الأرض؟",
    "answer_1": "أبو قبيس",
    "answer_2": "الطور",
    "answer_3": "أحد",
    "answer_4": "حراء",
    "right_answer": "أبو قبيس"
  },
  {
    "title": "ما هي عاصمة الدولة الأموية؟",
    "answer_1": "دمشق",
    "answer_2": "بغداد",
    "answer_3": "القاهرة",
    "answer_4": "المدينة",
    "right_answer": "دمشق"
  },
  {
    "title": "ما هي عاصمة الدولة العباسية؟",
    "answer_1": "بغداد",
    "answer_2": "دمشق",
    "answer_3": "القاهرة",
    "answer_4": "الكوفة",
    "right_answer": "بغداد"
  },
  {
    "title": "من هو النبي الذي أُرسل إلى قوم ثمود؟",
    "answer_1": "صالح",
    "answer_2": "هود",
    "answer_3": "شعيب",
    "answer_4": "لوط",
    "right_answer": "صالح"
  },
  {
    "title": "من هو النبي الذي أُرسل إلى قوم عاد؟",
    "answer_1": "هود",
    "answer_2": "صالح",
    "answer_3": "شعيب",
    "answer_4": "موسى",
    "right_answer": "هود"
  },
  {
    "title": "من هو النبي الذي أُرسل إلى أهل مدين؟",
    "answer_1": "شعيب",
    "answer_2": "لوط",
    "answer_3": "هود",
    "answer_4": "صالح",
    "right_answer": "شعيب"
  },
  {
    "title": "من هو النبي الذي ابتلعه الحوت؟",
    "answer_1": "يونس",
    "answer_2": "أيوب",
    "answer_3": "يحيى",
    "answer_4": "زكريا",
    "right_answer": "يونس"
  },
  {
    "title": "كم عدد الرسل الذين ذكروا في القرآن؟",
    "answer_1": "25",
    "answer_2": "20",
    "answer_3": "30",
    "answer_4": "15",
    "right_answer": "25"
  },
  {
    "title": "من هو خاتم الأنبياء والمرسلين؟",
    "answer_1": "محمد ﷺ",
    "answer_2": "عيسى عليه السلام",
    "answer_3": "موسى عليه السلام",
    "answer_4": "إبراهيم عليه السلام",
    "right_answer": "محمد ﷺ"
  },
  {
    "title": "من هو أول البشر؟",
    "answer_1": "آدم عليه السلام",
    "answer_2": "نوح عليه السلام",
    "answer_3": "إدريس عليه السلام",
    "answer_4": "شيث عليه السلام",
    "right_answer": "آدم عليه السلام"
  },
  {
    "title": "من هو النبي الذي كان يعمل نجاراً؟",
    "answer_1": "زكريا عليه السلام",
    "answer_2": "نوح عليه السلام",
    "answer_3": "داود عليه السلام",
    "answer_4": "محمد ﷺ",
    "right_answer": "زكريا عليه السلام"
  },
  {
    "title": "من هو النبي الذي كان يعمل حداداً؟",
    "answer_1": "داود عليه السلام",
    "answer_2": "سليمان عليه السلام",
    "answer_3": "إدريس عليه السلام",
    "answer_4": "نوح عليه السلام",
    "right_answer": "داود عليه السلام"
  },
  {
    "title": "من هو النبي الذي كان يعمل خياطاً؟",
    "answer_1": "إدريس عليه السلام",
    "answer_2": "آدم عليه السلام",
    "answer_3": "شعيب عليه السلام",
    "answer_4": "موسى عليه السلام",
    "right_answer": "إدريس عليه السلام"
  },
  {
    "title": "كم عدد أولاد إبراهيم عليه السلام المشهورين؟",
    "answer_1": "2",
    "answer_2": "3",
    "answer_3": "1",
    "answer_4": "4",
    "right_answer": "2"
  },
  {
    "title": "من هو والد النبي يوسف عليه السلام؟",
    "answer_1": "يعقوب",
    "answer_2": "إسحاق",
    "answer_3": "إبراهيم",
    "answer_4": "داود",
    "right_answer": "يعقوب"
  },
  {
    "title": "ما هي السورة التي بدأت بـ 'المر'؟",
    "answer_1": "الرعد",
    "answer_2": "يونس",
    "answer_3": "هود",
    "answer_4": "يوسف",
    "right_answer": "الرعد"
  },
  {
    "title": "ما هي السورة التي بدأت بـ 'المص'؟",
    "answer_1": "الأعراف",
    "answer_2": "البقرة",
    "answer_3": "آل عمران",
    "answer_4": "العنكبوت",
    "right_answer": "الأعراف"
  },
  {
    "title": "ما هي السورة التي بدأت بـ 'كهيعص'؟",
    "answer_1": "مريم",
    "answer_2": "طه",
    "answer_3": "يس",
    "answer_4": "الأنبياء",
    "right_answer": "مريم"
  },
  {
    "title": "ما هي السورة التي بدأت بـ 'طه'؟",
    "answer_1": "طه",
    "answer_2": "النور",
    "answer_3": "النمل",
    "answer_4": "الفرقان",
    "right_answer": "طه"
  },
  {
    "title": "ما هي السورة التي بدأت بـ 'يس'؟",
    "answer_1": "يس",
    "answer_2": "الواقعة",
    "answer_3": "الملك",
    "answer_4": "الرحمن",
    "right_answer": "يس"
  },
  {
    "title": "ما هو ترتيب سورة الفاتحة في القرآن؟",
    "answer_1": "1",
    "answer_2": "114",
    "answer_3": "50",
    "answer_4": "2",
    "right_answer": "1"
  },
  {
    "title": "ما هو ترتيب سورة الناس في القرآن؟",
    "answer_1": "114",
    "answer_2": "1",
    "answer_3": "100",
    "answer_4": "113",
    "right_answer": "114"
  },
  {
    "title": "كم مرة ذكر اسم النبي محمد ﷺ صراحة في القرآن؟",
    "answer_1": "4",
    "answer_2": "5",
    "answer_3": "10",
    "answer_4": "1",
    "right_answer": "4"
  },
  {
    "title": "ما هي السورة التي تسمى 'سورة السجدة'؟",
    "answer_1": "السجدة",
    "answer_2": "فصلت",
    "answer_3": "النجم",
    "answer_4": "العلق",
    "right_answer": "السجدة"
  },
  {
    "title": "ما هي السورة التي تسمى 'سورة المنافقون'؟",
    "answer_1": "المنافقون",
    "answer_2": "التوبة",
    "answer_3": "الجمعة",
    "answer_4": "الصف",
    "right_answer": "المنافقون"
  },
  {
    "title": "من هو النبي الذي أُعطي نصف الجمال؟",
    "answer_1": "يوسف عليه السلام",
    "answer_2": "محمد ﷺ",
    "answer_3": "عيسى عليه السلام",
    "answer_4": "إسماعيل عليه السلام",
    "right_answer": "يوسف عليه السلام"
  }
]
